[{"id":1,"name":"But Justice","owner":"Craig"},{"id":2,"name":"Sad Sacks","owner":"Keith"},{"id":4,"name":"Dancing Homers","owner":"Doug"},{"id":5,"name":"East Lancing Laughing Llamas","owner":"Jack"},{"id":6,"name":"clowndog & banjo","owner":"Jason"},{"id":7,"name":"Neon Tetras","owner":"Mike"},{"id":8,"name":"Dancing Homers","owner":"Doug"},{"id":9,"name":"Liquor Crickets","owner":"Chris"},{"id":10,"name":"Crap Shooters","owner":"Calvin"},{"id":11,"name":"Natural Catching Position","owner":"Dan"},{"id":12,"name":"Chris' Mom for $1","owner":"Andrew"},{"id":13,"name":"Hogan's Heroes","owner":"Bill"},{"id":14,"name":"Nacho Helmet","owner":"Corey"},{"id":15,"name":"Fluffy the Destroyer","owner":"Scott"},{"id":16,"name":"Nosferatu","owner":"Jeff"},{"id":17,"name":"Dicks Out for Harambe","owner":"Kirk"}]